mrio_toolbox/__init__.py
mrio_toolbox/mrio.py
mrio_toolbox/_parts/_Axe.py
mrio_toolbox/_parts/_Part.py
mrio_toolbox/_parts/__init__.py
mrio_toolbox/_parts/part_operations.py
mrio_toolbox/extractors/__init__.py
mrio_toolbox/extractors/downloaders.py
mrio_toolbox/extractors/extractors.py
mrio_toolbox/extractors/emerging/__init__.py
mrio_toolbox/extractors/emerging/emerging_extractor.py
mrio_toolbox/extractors/eora/__init__.py
mrio_toolbox/extractors/eora/eora_extractor.py
mrio_toolbox/extractors/exiobase/__init__.py
mrio_toolbox/extractors/exiobase/exiobase_extractor.py
mrio_toolbox/extractors/figaro/__init__.py
mrio_toolbox/extractors/figaro/figaro_downloader.py
mrio_toolbox/extractors/figaro/figaro_extractor.py
mrio_toolbox/extractors/gloria/__init__.py
mrio_toolbox/extractors/gloria/gloria_extractor.py
mrio_toolbox/extractors/gtap11/__init__.py
mrio_toolbox/extractors/gtap11/extraction/__init__.py
mrio_toolbox/extractors/gtap11/extraction/extractor.py
mrio_toolbox/extractors/gtap11/extraction/harpy_files/__init__.py
mrio_toolbox/extractors/gtap11/extraction/harpy_files/_header_sets.py
mrio_toolbox/extractors/gtap11/extraction/harpy_files/har_file.py
mrio_toolbox/extractors/gtap11/extraction/harpy_files/har_file_io.py
mrio_toolbox/extractors/gtap11/extraction/harpy_files/header_array.py
mrio_toolbox/extractors/gtap11/extraction/harpy_files/sl4.py
mrio_toolbox/extractors/gtap11/gtap_mrio/__init__.py
mrio_toolbox/extractors/gtap11/gtap_mrio/mrio_builder.py
mrio_toolbox/extractors/icio/__init__.py
mrio_toolbox/extractors/icio/icio_extractor.py
mrio_toolbox/extractors/wiod/__init__.py
mrio_toolbox/extractors/wiod/wiod_extractor.py
mrio_toolbox/msm/__init__.py
mrio_toolbox/msm/multi_scale_mapping.py
mrio_toolbox/utils/__init__.py
mrio_toolbox/utils/converters/__init__.py
mrio_toolbox/utils/converters/pandas.py
mrio_toolbox/utils/converters/xarray.py
mrio_toolbox/utils/formatting/__init__.py
mrio_toolbox/utils/formatting/formatter.py
mrio_toolbox-1.1.6.dist-info/licenses/LICENSE
mrio_toolbox-1.1.6.dist-info/METADATA
mrio_toolbox-1.1.6.dist-info/WHEEL
mrio_toolbox-1.1.6.dist-info/top_level.txt
mrio_toolbox-1.1.6.dist-info/RECORD
